MANIFEST.in
README.md
setup.py
gathercontent/__init__.py
gathercontent/client.py
gathercontent/test.py
gathercontent.egg-info/PKG-INFO
gathercontent.egg-info/SOURCES.txt
gathercontent.egg-info/dependency_links.txt
gathercontent.egg-info/not-zip-safe
gathercontent.egg-info/requires.txt
gathercontent.egg-info/top_level.txt