Metadata-Version: 1.1
Name: gathercontent
Version: 0.2
Summary: A very simple API wrapper for Gather Content
Home-page: http://bitbucket.org/wearefarm/gathercontent
Author: Jon Atkinson
Author-email: jon@wearefarm.com
License: MIT
Keywords: gather content gathercontent
Platform: UNKNOWN
Classifier: Development Status :: 3 - Alpha
Classifier: License :: OSI Approved :: MIT License
Classifier: Programming Language :: Python :: 2.7
